karaoke_prep/__init__.py
karaoke_prep/karaoke_finalise/__init__.py
karaoke_prep/karaoke_finalise/karaoke_finalise.py
karaoke_prep/karaoke_prep.py
karaoke_prep/resources/AvenirNext-Bold.ttf
karaoke_prep/resources/Montserrat-Bold.ttf
karaoke_prep/resources/Oswald-Bold.ttf
karaoke_prep/resources/Oswald-SemiBold.ttf
karaoke_prep/resources/Zurich_Cn_BT_Bold.ttf
karaoke_prep/utils/__init__.py
karaoke_prep/utils/auto_cli.py
karaoke_prep/utils/bulk_cli.py
karaoke_prep/utils/finalise_cli.py
karaoke_prep/utils/prep_cli.py
karaoke_prep-0.44.0.dist-info/LICENSE
karaoke_prep-0.44.0.dist-info/METADATA
karaoke_prep-0.44.0.dist-info/WHEEL
karaoke_prep-0.44.0.dist-info/entry_points.txt
karaoke_prep-0.44.0.dist-info/RECORD
