Metadata-Version: 2.3
Name: karaoke-prep
Version: 0.44.0
Summary: Prepare for karaoke video creation, by downloading audio and lyrics for a specified song or playlist from youtube and separating audio stems. After syncing, finalise the video with a title screen!
License: MIT
Author: Andrew Beveridge
Author-email: andrew@beveridge.uk
Requires-Python: >=3.10,<3.13
Classifier: License :: OSI Approved :: MIT License
Classifier: Programming Language :: Python :: 3
Classifier: Programming Language :: Python :: 3.10
Classifier: Programming Language :: Python :: 3.11
Classifier: Programming Language :: Python :: 3.12
Requires-Dist: argparse (>=1.4.0)
Requires-Dist: attrs (>=24.2.0)
Requires-Dist: audio-separator[cpu] (>=0.21.0)
Requires-Dist: beautifulsoup4 (>=4)
Requires-Dist: cattrs (>=24.1.2)
Requires-Dist: fetch-lyrics-from-genius (>=0.1)
Requires-Dist: google-api-python-client
Requires-Dist: google-auth
Requires-Dist: google-auth-httplib2
Requires-Dist: google-auth-oauthlib
Requires-Dist: kbputils (>=0.0.16,<0.0.17)
Requires-Dist: lyrics-converter (>=0.2.1)
Requires-Dist: lyrics-transcriber (>=0.34)
Requires-Dist: lyricsgenius (>=3)
Requires-Dist: numpy (>=1,<2)
Requires-Dist: pillow (>=10.1)
Requires-Dist: psutil (>=7.0.0,<8.0.0)
Requires-Dist: pyinstaller (>=6.3)
Requires-Dist: requests (>=2)
Requires-Dist: thefuzz (>=0.22)
Requires-Dist: toml (>=0.10)
Requires-Dist: torch (<2.5)
Requires-Dist: yt-dlp
Project-URL: Documentation, https://github.com/karaokenerds/karaoke-prep/blob/main/README.md
Project-URL: Homepage, https://github.com/karaokenerds/karaoke-prep
Project-URL: Repository, https://github.com/karaokenerds/karaoke-prep
